nts/hardware/serial/__init__.py
nts/hardware/serial/py.typed
nts/hardware/serial/version.py
nts/hardware/serial/client/__init__.py
nts/hardware/serial/client/rs485_client.py
nts/hardware/serial/config/__init__.py
nts/hardware/serial/config/defaults.py
nts/hardware/serial/config/exceptions.py
nts/hardware/serial/config/serial_connection_implementation.py
nts/hardware/serial/config/serial_connection_interface.py
nts/hardware/serial/config/validation.py
nts/hardware/serial/server/__init__.py
nts/hardware/serial/server/modbus_datablock.py
nts/hardware/serial/server/rs485_server.py
nts/hardware/serial/utilities/__init__.py
nts/hardware/serial/utilities/checksum.py
nts/hardware/serial/utilities/mock.py
nts/hardware/serial/utilities/modbus.py
nts/hardware/serial/utilities/numeric.py
nts/hardware/serial/virtual/__init__.py
nts/hardware/serial/virtual/virtual_serial_network.py
nts/hardware/serial/virtual/virtual_serial_pair.py
nts/hardware/serial/virtual/worker.py
nts_hardware_serial-1.0.1.dist-info/LICENSE
nts_hardware_serial-1.0.1.dist-info/METADATA
nts_hardware_serial-1.0.1.dist-info/WHEEL
nts_hardware_serial-1.0.1.dist-info/top_level.txt
nts_hardware_serial-1.0.1.dist-info/RECORD
