Metadata-Version: 2.2
Name: nts.hardware.serial
Version: 1.0.1
Summary: Serial communication library
Author-email: Anton Bondarenko <bond.anton@gmail.com>
License: MIT License
Project-URL: Homepage, https://github.com/bond-anton/nts.hardware.serial
Project-URL: Bug Tracker, https://github.com/bond-anton/nts.hardware.serial/issues
Classifier: Programming Language :: Python :: 3
Classifier: License :: OSI Approved :: MIT License
Classifier: Operating System :: OS Independent
Requires-Python: >=3.9
License-File: LICENSE
Requires-Dist: pymodbus[serial]~=3.8.0
Provides-Extra: dev
Provides-Extra: test
Requires-Dist: flake8; extra == "test"
Requires-Dist: pytest; extra == "test"
Requires-Dist: pytest-asyncio; extra == "test"
Provides-Extra: lint
Requires-Dist: pylint; extra == "lint"
